{
    "os": "Linux-3.10.0-1160.90.1.el7.x86_64-x86_64-with-glibc2.17",
    "python": "3.9.16",
    "heartbeatAt": "2023-06-29T20:57:39.786130",
    "startedAt": "2023-06-29T20:57:39.263703",
    "docker": null,
    "cuda": "10.1.243",
    "args": [
        "--htune",
        "htune__dcgan__tinyaes",
        "--devices",
        "cuda:0",
        "cuda:1",
        "cuda:2"
    ],
    "state": "running",
    "program": "/local/a/jgammell/dlsca_bag_of_tricks/src/main.py",
    "codePath": "src/main.py",
    "git": {
        "remote": "https://github.com/jimgammell/dlsca_temperature_scaling",
        "commit": "fa68d435d48e3f1d7f2075395e957016f33dbe9f"
    },
    "email": "jgammell@purdue.edu",
    "root": "/local/a/jgammell/dlsca_bag_of_tricks",
    "host": "cbric-gpu1.ecn.purdue.edu",
    "username": "jgammell",
    "executable": "/home/min/a/jgammell/miniconda3/envs/sca-defense/bin/python",
    "cpu_count": 20,
    "cpu_count_logical": 40,
    "cpu_freq": {
        "current": 2012.266275,
        "min": 800.0,
        "max": 3000.0
    },
    "cpu_freq_per_core": [
        {
            "current": 2258.544,
            "min": 800.0,
            "max": 3000.0
        },
        {
            "current": 2177.844,
            "min": 800.0,
            "max": 3000.0
        },
        {
            "current": 2342.602,
            "min": 800.0,
            "max": 3000.0
        },
        {
            "current": 2571.813,
            "min": 800.0,
            "max": 3000.0
        },
        {
            "current": 2054.309,
            "min": 800.0,
            "max": 3000.0
        },
        {
            "current": 2070.69,
            "min": 800.0,
            "max": 3000.0
        },
        {
            "current": 2015.771,
            "min": 800.0,
            "max": 3000.0
        },
        {
            "current": 2068.273,
            "min": 800.0,
            "max": 3000.0
        },
        {
            "current": 2570.471,
            "min": 800.0,
            "max": 3000.0
        },
        {
            "current": 2157.299,
            "min": 800.0,
            "max": 3000.0
        },
        {
            "current": 2172.741,
            "min": 800.0,
            "max": 3000.0
        },
        {
            "current": 2192.211,
            "min": 800.0,
            "max": 3000.0
        },
        {
            "current": 1594.946,
            "min": 800.0,
            "max": 3000.0
        },
        {
            "current": 799.89,
            "min": 800.0,
            "max": 3000.0
        },
        {
            "current": 2254.785,
            "min": 800.0,
            "max": 3000.0
        },
        {
            "current": 2213.964,
            "min": 800.0,
            "max": 3000.0
        },
        {
            "current": 2147.363,
            "min": 800.0,
            "max": 3000.0
        },
        {
            "current": 1769.104,
            "min": 800.0,
            "max": 3000.0
        },
        {
            "current": 2416.723,
            "min": 800.0,
            "max": 3000.0
        },
        {
            "current": 2074.449,
            "min": 800.0,
            "max": 3000.0
        },
        {
            "current": 2331.188,
            "min": 800.0,
            "max": 3000.0
        },
        {
            "current": 2524.816,
            "min": 800.0,
            "max": 3000.0
        },
        {
            "current": 2228.332,
            "min": 800.0,
            "max": 3000.0
        },
        {
            "current": 2159.985,
            "min": 800.0,
            "max": 3000.0
        },
        {
            "current": 2173.01,
            "min": 800.0,
            "max": 3000.0
        },
        {
            "current": 2236.12,
            "min": 800.0,
            "max": 3000.0
        },
        {
            "current": 2068.139,
            "min": 800.0,
            "max": 3000.0
        },
        {
            "current": 2066.931,
            "min": 800.0,
            "max": 3000.0
        },
        {
            "current": 1987.438,
            "min": 800.0,
            "max": 3000.0
        },
        {
            "current": 1987.036,
            "min": 800.0,
            "max": 3000.0
        },
        {
            "current": 2301.379,
            "min": 800.0,
            "max": 3000.0
        },
        {
            "current": 1633.081,
            "min": 800.0,
            "max": 3000.0
        },
        {
            "current": 2153.54,
            "min": 800.0,
            "max": 3000.0
        },
        {
            "current": 927.185,
            "min": 800.0,
            "max": 3000.0
        },
        {
            "current": 803.112,
            "min": 800.0,
            "max": 3000.0
        },
        {
            "current": 2259.216,
            "min": 800.0,
            "max": 3000.0
        },
        {
            "current": 2173.681,
            "min": 800.0,
            "max": 3000.0
        },
        {
            "current": 1761.584,
            "min": 800.0,
            "max": 3000.0
        },
        {
            "current": 1761.718,
            "min": 800.0,
            "max": 3000.0
        },
        {
            "current": 2180.395,
            "min": 800.0,
            "max": 3000.0
        }
    ],
    "disk": {
        "total": 63.515846252441406,
        "used": 40.23428726196289
    },
    "gpu": "NVIDIA GeForce GTX 1080 Ti",
    "gpu_count": 3,
    "gpu_devices": [
        {
            "name": "NVIDIA GeForce GTX 1080 Ti",
            "memory_total": 11811160064
        },
        {
            "name": "NVIDIA GeForce GTX 1080 Ti",
            "memory_total": 11811160064
        },
        {
            "name": "NVIDIA GeForce GTX 1080 Ti",
            "memory_total": 11811160064
        }
    ],
    "memory": {
        "total": 92.8799934387207
    }
}
